tic_toc_timer/__init__.py
tic_toc_timer/timer.py
tic_toc_timer/timer_test.py
TicTocTimer-0.1.4.dist-info/METADATA
TicTocTimer-0.1.4.dist-info/WHEEL
TicTocTimer-0.1.4.dist-info/top_level.txt
TicTocTimer-0.1.4.dist-info/RECORD
