Metadata-Version: 2.1
Name: TicTocTimer
Version: 0.1.4
Summary: A timer object for python, with similar syntax to matlab's tic toc
Home-page: https://github.com/LamaAni/TicTocTimer
Author: Zav Shotan
Author-email: 
License: LICENSE
Platform: any
Requires-Python: >=3.6
